victor_smart_kill/__init__.py
victor_smart_kill/_api.py
victor_smart_kill/_client.py
victor_smart_kill/_models.py
victor_smart_kill/py.typed
victor_smart_kill-2021.11.0.dist-info/LICENSE
victor_smart_kill-2021.11.0.dist-info/METADATA
victor_smart_kill-2021.11.0.dist-info/WHEEL
victor_smart_kill-2021.11.0.dist-info/top_level.txt
victor_smart_kill-2021.11.0.dist-info/RECORD
