Metadata-Version: 2.1
Name: victor-smart-kill
Version: 2021.11.0
Summary: A simple unofficial async Python wrapper for Victor Smart-Kill API.
Home-page: https://github.com/toreamun/victor-smart-kill
Author: Tore Amundsen
Author-email: tore@amundsen.org
License: UNKNOWN
Keywords: API,Victor Smart-Kill,VictorPest.com,trap
Platform: UNKNOWN
Classifier: Programming Language :: Python :: 3
Classifier: License :: OSI Approved :: MIT License
Classifier: Operating System :: OS Independent
Requires-Python: >=3.6
License-File: LICENSE
Requires-Dist: httpx (>=0.20.*)
Requires-Dist: marshmallow (>=3.8)
Requires-Dist: marshmallow-dataclass[enum,union] (>=8.1)
